reportclassicproject/__init__.py
reportclassicproject/report_classic.py
reportclassicproject/report_label.py
reportclassicproject/report_line_detail.py
reportclassicproject/report_mline_detail.py
reportclassicproject-0.2.dist-info/LICENSE.txt
reportclassicproject-0.2.dist-info/METADATA
reportclassicproject-0.2.dist-info/WHEEL
reportclassicproject-0.2.dist-info/top_level.txt
reportclassicproject-0.2.dist-info/RECORD
